LICENSE.txt
MANIFEST.in
README.rst
requirements-test.txt
setup.cfg
setup.py
tox.ini
docs/Makefile
docs/apidefinitions.rst
docs/cli.rst
docs/conf.py
docs/configuration.rst
docs/contribute.rst
docs/dpaygo.account.rst
docs/dpaygo.aes.rst
docs/dpaygo.amount.rst
docs/dpaygo.asciichart.rst
docs/dpaygo.asset.rst
docs/dpaygo.block.rst
docs/dpaygo.blockchain.rst
docs/dpaygo.blockchainobject.rst
docs/dpaygo.comment.rst
docs/dpaygo.conveyor.rst
docs/dpaygo.discussions.rst
docs/dpaygo.dpay.rst
docs/dpaygo.dpayid.rst
docs/dpaygo.exceptions.rst
docs/dpaygo.imageuploader.rst
docs/dpaygo.instance.rst
docs/dpaygo.market.rst
docs/dpaygo.memo.rst
docs/dpaygo.message.rst
docs/dpaygo.nodelist.rst
docs/dpaygo.notify.rst
docs/dpaygo.price.rst
docs/dpaygo.snapshot.rst
docs/dpaygo.storage.rst
docs/dpaygo.transactionbuilder.rst
docs/dpaygo.utils.rst
docs/dpaygo.vote.rst
docs/dpaygo.wallet.rst
docs/dpaygo.witness.rst
docs/dpaygoapi.dpaynoderpc.rst
docs/dpaygoapi.exceptions.rst
docs/dpaygoapi.graphenenerpc.rst
docs/dpaygoapi.node.rst
docs/dpaygoapi.websocket.rst
docs/dpaygobase.memo.rst
docs/dpaygobase.objects.rst
docs/dpaygobase.objecttypes.rst
docs/dpaygobase.operationids.rst
docs/dpaygobase.operations.rst
docs/dpaygobase.signedtransactions.rst
docs/dpaygobase.transactions.rst
docs/dpaygographenebase.account.rst
docs/dpaygographenebase.base58.rst
docs/dpaygographenebase.bip38.rst
docs/dpaygographenebase.ecdsasig.rst
docs/dpaygographenebase.objects.rst
docs/dpaygographenebase.objecttypes.rst
docs/dpaygographenebase.operations.rst
docs/dpaygographenebase.signedtransactions.rst
docs/index.hbs
docs/index.rst
docs/indices.rst
docs/installation.rst
docs/make.bat
docs/modules.rst
docs/quickstart.rst
docs/requirements.txt
docs/support.rst
docs/tutorials.rst
docs/_static/dpaygo-icon.png
docs/_static/dpaygo-icon_bw.png
docs/_static/dpaygo-logo.png
docs/_static/dpaygo-logo.svg
docs/_static/dpaygo-logo_2.png
docs/_static/dpaygo-logo_2.svg
docs/_static/dpaygo-logo_bw.png
docs/_static/dpaygo-logo_bw.svg
dpaygo.egg-info/PKG-INFO
dpaygo.egg-info/SOURCES.txt
dpaygo.egg-info/dependency_links.txt
dpaygo.egg-info/entry_points.txt
dpaygo.egg-info/requires.txt
dpaygo.egg-info/top_level.txt
