Metadata-Version: 1.2
Name: dpaygo
Version: 0.1.22
Summary: Unofficial Python library for dPay
Home-page: http://www.github.com/dpays/dpaygo
Author: Jared Rice Sr.
Author-email: jared@benchx.io
Maintainer: Jared Rice Sr.
Maintainer-email: jared@benchx.io
License: UNKNOWN
Download-URL: https://github.com/dpays/dpaygo/tarball/0.01.22
Keywords: dpay,library,api,rpc
Platform: UNKNOWN
Classifier: License :: OSI Approved :: MIT License
Classifier: Operating System :: OS Independent
Classifier: Programming Language :: Python
Classifier: Programming Language :: Python :: 2.7
Classifier: Programming Language :: Python :: 3
Classifier: Programming Language :: Python :: 3.4
Classifier: Programming Language :: Python :: 3.5
Classifier: Programming Language :: Python :: 3.6
Classifier: Development Status :: 4 - Beta
Classifier: Intended Audience :: Developers
Classifier: Intended Audience :: Financial and Insurance Industry
Classifier: Topic :: Office/Business :: Financial
